{
    "commonAdjectives": [
        "Foolish",
        "Excellent",
        "Deathly",
        "Deadly",
        "Smart",
        "Intelligent",
        "Sweet",
        "Banished",
        "Official",
        "Officious",
        "Cannibalistic",
        "Unepic",
        "Terrific",
        "French",
        "Holy",
        "Epic",
        "Slumbering",
        "High Peak",
        "Hollow",
        "Legendary",
        "Primal",
        "Cursed",
        "Deprecated",
        "Soft",
        "Hard",
        "Deep",
        "Hazardous",
        "Unexpected",
        "Unbelievable",
        "Nice",
        "Special",
        "Independent",
        "Hardy",
        "Incompetent",
        "Impotent",
        "Condemned",
        "Great",
        "Mild",
        "Amazing",
        "Incredible",
        "Crazy",
        "Marvelous",
        "Poor",
        "Strong",
        "Weak",
        "Plausible",
        "Elite",
        "Shallow",
        "Glorious",
        "Bloody",
        "Toxic",
        "Swift",
        "Exquisite",
        "Caustic",
        "Risible",
        "Laughable",
        "Platitudinous",
        "Nefarious",
        "Wicked",
        "Ancient"
    ],
    "duelAdjectives": [
        "Rainbow",
        "Pretty",
        "Colorful",
        "Misty",
        "Burning",
        "Crimson",
        "Exciting",
        "Huge"
    ],
    "humanAdjectives": [
        "Clever",
        "Old",
        "Guileless",
        "Zealous",
        "Famous",
        "Adroit",
        "Resourceful",
        "Naive",
        "Clingy",
        "Dead",
        "Cynical",
        "Reliable",
        "Grumpy",
        "Unreliable",
        "Witty",
        "Sincere",
        "Sympathetic",
        "Courageous",
        "Ambitious",
        "Brave",
        "Reckless",
        "Adventurous",
        "Lucky",
        "Cunning",
        "Unhinged",
        "Frontline",
        "Arch",
        "Alpha",
        "Undead"
    ],
    "humanNouns": [
        "Demons",
        "Magistrates of Death",
        "Screaming Skulls",
        "Librarians",
        "Yeeters",
        "Void",
        "Jerkshrooms",
        "Blowgunners",
        "Ticks",
        "Giant Ticks",
        "Mama Ticks",
        "Zombies",
        "Inquisitors",
        "Bad Seeds",
        "Tentacles",
        "Automatons",
        "Royal Guards",
        "Bombers",
        "Slammers",
        "Ground Shakers",
        "Rampagers",
        "Failed Experiments",
        "Elites",
        "Fools",
        "Archers",
        "Sandals",
        "Frontlines",
        "Wizards",
        "Battle Mages",
        "Heralds",
        "Guardians",
        "Crusaders",
        "Archons",
        "Legends",
        "Ancients",
        "Divinities",
        "Immortals",
        "Priests",
        "Mages",
        "Crimson Demons",
        "Thieves",
        "Bananas",
        "Monkeys",
        "Spoiler Bosses",
        "Collectors",
        "Bombers",
        "Arbiters",
        "Horses",
        "Weebs",
        "Warriors",
        "Conquerors",
        "Swordsmen",
        "Chat Members",
        "Friends",
        "Ghosts",
        "Special Friends",
        "Catapults",
        "Neypahs",
        "Watchers",
        "Hands of the King",
        "Assassins",
        "Keepers",
        "Time Keepers",
        "Golems",
        "Guardians",
        "Giants",
        "Midgets",
        "Kings",
        "Keepers",
        "Incomplete Ones",
        "Cowards",
        "Rangers",
        "Dead Brain Cells",
        "Knights",
        "Biters",
        "Shieldbearers",
        "Phazers",
        "Defenders",
        "Catchers",
        "Cleavers",
        "Kamikazes",
        "Scorpions",
        "Worms",
        "Spikers",
        "Mushrooms",
        "Plants",
        "Slashers",
        "Shockers",
        "Thornies",
        "Foggers",
        "Spinners",
        "Bombardiers",
        "Casters",
        "Lancers",
        "Screamers",
        "Cannibals",
        "Gods",
        "Baguettes",
        "Croissants",
        "Ramparts",
        "Unicorns",
        "Architects",
        "Warchasers"
    ],
    "placeNouns": [
        "Sunshine",
        "Night",
        "Prison",
        "Sewers",
        "Graveyard",
        "Cavern",
        "Clock Tower"
    ],
    "coreNouns": [
        "Argument",
        "Fencing",
        "Bout",
        "Competition",
        "Strife",
        "Symphony",
        "Discord",
        "Silksong",
        "Will",
        "Disagreement",
        "Contest",
        "Conflict",
        "Feud",
        "Flame War",
        "Encounter",
        "Duel",
        "Quarrel",
        "Disunity",
        "Corruption",
        "Meeting",
        "Hazard",
        "Binding",
        "Brawl",
        "Trial",
        "Battle",
        "Battle Royale",
        "Fight",
        "Confrontation",
        "Affair",
        "Challenge",
        "Combat",
        "Tableflip"
    ]
}
